petal_user_journey_coordinator-0.1.8.dist-info/METADATA
petal_user_journey_coordinator-0.1.8.dist-info/WHEEL
petal_user_journey_coordinator-0.1.8.dist-info/entry_points.txt
petal_user_journey_coordinator/__init__.py
petal_user_journey_coordinator/controllers.py
petal_user_journey_coordinator/data_model.py
petal_user_journey_coordinator/plugin.py
petal_user_journey_coordinator-0.1.8.dist-info/RECORD
