Metadata-Version: 2.1
Name: petal-user-journey-coordinator
Version: 0.1.8
Summary: A petal for the DroneLeaf ecosystem
Author-Email: Khalil Al Handawi <khalil.alhandawi@droneleaf.io>
License: MIT
Requires-Python: >=3.10
Requires-Dist: numpy>=2.2.6
Requires-Dist: matplotlib>=3.10.6
